rx784/__about__.py
rx784/__init__.py
rx784/button.py
rx784/command.py
rx784/device.py
rx784/key_code.py
rx784/keyboard_led.py
rx784/state.py
rx784/status.py
rx784-1.2.0.dist-info/METADATA
rx784-1.2.0.dist-info/WHEEL
rx784-1.2.0.dist-info/licenses/LICENSE.txt
rx784-1.2.0.dist-info/RECORD
